simpleactors.py
simpleactors-0.1.2.dist-info/METADATA
simpleactors-0.1.2.dist-info/top_level.txt
simpleactors-0.1.2.dist-info/WHEEL
simpleactors-0.1.2.dist-info/metadata.json
simpleactors-0.1.2.dist-info/RECORD
simpleactors-0.1.2.dist-info/DESCRIPTION.rst
